osintradar/__init__.py
osintradar/c2intelfeeds.py
osintradar/feodotracker.py
osintradar/malwarebazaar.py
osintradar/openphish.py
osintradar/phishingdatabase.py
osintradar/phishstats.py
osintradar/phishunt.py
osintradar/sslblacklist.py
osintradar/threatview.py
osintradar/tweetfeed.py
osintradar/urlhaus.py
osintradar/usom.py
osintradar/vxvault.py
osintradar-0.1.dist-info/LICENSE
osintradar-0.1.dist-info/METADATA
osintradar-0.1.dist-info/WHEEL
osintradar-0.1.dist-info/top_level.txt
osintradar-0.1.dist-info/RECORD
